{
  "biome.wilderwild.cypress_wetlands": "Zypressensumpf",
  "biome.wilderwild.mixed_forest": "Mischwald",
  "biome.wilderwild.jellyfish_caves": "Quallenhöhlen",
  "biome.wilderwild.oasis": "Oasis",
  "biome.wilderwild.warm_river": "Warm River",
  "biome.wilderwild.warm_beach": "Warmer Strand",
  "biome.wilderwild.birch_taiga": "Birch Taiga",
  "biome.wilderwild.old_growth_birch_taiga": "Birken-Urtaiga",
  "biome.wilderwild.birch_jungle": "Birkendschungel",
  "biome.wilderwild.sparse_birch_jungle": "Karger Birkendschungel",
  "biome.wilderwild.flower_field": "Blumenfeld",
  "biome.wilderwild.arid_savanna": "Arid Savanna",
  "biome.wilderwild.parched_forest": "Ausgedorrter Wald",
  "biome.wilderwild.arid_forest": "Trockenwald",
  "biome.wilderwild.snowy_old_growth_pine_taiga": "Verschneite Kiefern-Urtaiga",
  "biome.wilderwild.old_growth_dark_forest": "Dunkler Urwald",
  "biome.wilderwild.dark_birch_forest": "Dunkler Birkenwald",
  "biome.wilderwild.semi_birch_forest": "Semi Birch Forest",
  "biome.wilderwild.temperate_rainforest": "Gemäßigter Regenwald",
  "biome.wilderwild.rainforest": "Rainforest",
  "biome.wilderwild.dark_taiga": "Dunkle Taiga",
  "biome.wilderwild.dying_forest": "Sterbender Wald",
  "biome.wilderwild.snowy_dying_forest": "Verschneiter sterbender Wald",
  "biome.wilderwild.dying_mixed_forest": "Sterbender Mischwald",
  "biome.wilderwild.snowy_dying_mixed_forest": "Verschneiter sterbender Mischwald",
  "block.wilderwild.alba_glory_of_the_snow": "Weißer Schneestolz",
  "block.wilderwild.algae": "Algae",
  "block.wilderwild.baobab_button": "Baobab Button",
  "block.wilderwild.baobab_door": "Baobab Door",
  "block.wilderwild.baobab_fence": "Baobab Fence",
  "block.wilderwild.baobab_fence_gate": "Baobab Fence Gate",
  "block.wilderwild.baobab_hanging_sign": "Baobab Hanging Sign",
  "block.wilderwild.baobab_leaves": "Baobab Leaves",
  "block.wilderwild.baobab_log": "Baobab Log",
  "block.wilderwild.baobab_nut": "Baobabnuss",
  "block.wilderwild.baobab_planks": "Baobab Planks",
  "block.wilderwild.baobab_pressure_plate": "Baobab Pressure Plate",
  "block.wilderwild.baobab_sign": "Baobab Sign",
  "block.wilderwild.baobab_slab": "Baobab Slab",
  "block.wilderwild.baobab_stairs": "Baobab Stairs",
  "block.wilderwild.baobab_trapdoor": "Baobab Trapdoor",
  "block.wilderwild.baobab_wall_hanging_sign": "Baobabholzwandhängeschild",
  "block.wilderwild.baobab_wall_sign": "Baobabholzwandschild",
  "block.wilderwild.baobab_wood": "Baobab Wood",
  "block.wilderwild.blue_giant_glory_of_the_snow": "Blauer Schneestolz",
  "block.wilderwild.brown_shelf_fungus": "Brauner Porling",
  "block.wilderwild.bush": "Bush",
  "block.wilderwild.carnation": "Carnation",
  "block.wilderwild.cattail": "Cattail",
  "block.wilderwild.chiseled_mud_bricks": "Chiseled Mud Bricks",
  "block.wilderwild.cypress_button": "Cypress Button",
  "block.wilderwild.cypress_door": "Cypress Door",
  "block.wilderwild.cypress_fence": "Cypress Fence",
  "block.wilderwild.cypress_fence_gate": "Cypress Fence Gate",
  "block.wilderwild.cypress_hanging_sign": "Cypress Hanging Sign",
  "block.wilderwild.cypress_leaves": "Cypress Leaves",
  "block.wilderwild.cypress_log": "Cypress Log",
  "block.wilderwild.cypress_planks": "Cypress Planks",
  "block.wilderwild.cypress_pressure_plate": "Cypress Pressure Plate",
  "block.wilderwild.cypress_roots": "Zypressenwurzeln",
  "block.wilderwild.cypress_sapling": "Cypress Sapling",
  "block.wilderwild.cypress_sign": "Cypress Sign",
  "block.wilderwild.cypress_slab": "Cypress Slab",
  "block.wilderwild.cypress_stairs": "Cypress Stairs",
  "block.wilderwild.cypress_trapdoor": "Cypress Trapdoor",
  "block.wilderwild.cypress_wall_hanging_sign": "Zypressenholzwandhängeschild",
  "block.wilderwild.cypress_wall_sign": "Zypressenholzwandschild",
  "block.wilderwild.cypress_wood": "Zypressenholz",
  "block.wilderwild.datura": "Tollkraut",
  "block.wilderwild.display_lantern": "Schaukastenlaterne",
  "block.wilderwild.echo_glass": "Echoglas",
  "block.wilderwild.flowering_lily_pad": "Flowering Lily Pad",
  "block.wilderwild.glory_of_the_snow": "Schneestolz",
  "block.wilderwild.hanging_tendril": "Hanging Tendril",
  "block.wilderwild.hollowed_acacia_log": "Ausgehöhlter Akazienstamm",
  "block.wilderwild.hollowed_baobab_log": "Ausgehöhlter Baobabstamm",
  "block.wilderwild.hollowed_birch_log": "Ausgehöhlter Birkenstamm",
  "block.wilderwild.hollowed_cherry_log": "Ausgehöhlter Kirschstamm",
  "block.wilderwild.hollowed_cypress_log": "Ausgehöhlter Zypressenstamm",
  "block.wilderwild.hollowed_dark_oak_log": "Ausgehöhlter Schwarzeichenstamm",
  "block.wilderwild.hollowed_jungle_log": "Ausgehöhlter Tropenbaumstamm",
  "block.wilderwild.hollowed_mangrove_log": "Ausgehöhlter Mangrovenstamm",
  "block.wilderwild.hollowed_crimson_stem": "Ausgehöhlter Karmesinstiel",
  "block.wilderwild.hollowed_warped_stem": "Ausgehöhlter Wirrstiel",
  "block.wilderwild.hollowed_oak_log": "Ausgehöhlter Eichenstamm",
  "block.wilderwild.hollowed_spruce_log": "Ausgehöhlter Fichtenstamm",
  "block.wilderwild.hollowed_palm_log": "Ausgehöhlter Palmbaumstamm",
  "block.wilderwild.stripped_hollowed_acacia_log": "Entrindeter ausgehöhlter Akazienstamm",
  "block.wilderwild.stripped_hollowed_baobab_log": "Entrindeter ausgehöhlter Baobabstamm",
  "block.wilderwild.stripped_hollowed_birch_log": "Entrindeter ausgehöhlter Birkenstamm",
  "block.wilderwild.stripped_hollowed_cherry_log": "Entrindeter ausgehöhlter Kirschstamm",
  "block.wilderwild.stripped_hollowed_cypress_log": "Entrindeter ausgehöhlter Zypressenstamm",
  "block.wilderwild.stripped_hollowed_dark_oak_log": "Entrindeter ausgehöhlter Schwarzeichenstamm",
  "block.wilderwild.stripped_hollowed_jungle_log": "Entrindeter ausgehöhlter Tropenbaumstamm",
  "block.wilderwild.stripped_hollowed_mangrove_log": "Entrindeter ausgehöhlter Mangrovenstamm",
  "block.wilderwild.stripped_hollowed_crimson_stem": "Entrindeter ausgehöhlter Karmesinstiel",
  "block.wilderwild.stripped_hollowed_warped_stem": "Entrindeter ausgehöhlter Wirrstiel",
  "block.wilderwild.stripped_hollowed_oak_log": "Entrindeter ausgehöhlter Eichenstamm",
  "block.wilderwild.stripped_hollowed_spruce_log": "Entrindeter ausgehöhlter Fichtenstamm",
  "block.wilderwild.stripped_hollowed_palm_log": "Entrindeter ausgehöhlter Palmbaumstamm",
  "block.wilderwild.milkweed": "Seidenpflanze",
  "block.wilderwild.null_block": "Null Block",
  "block.wilderwild.osseous_sculk": "Osseous Sculk",
  "block.wilderwild.ostrich_egg": "Ostrich Egg",
  "block.wilderwild.palm_button": "Palm Button",
  "block.wilderwild.palm_door": "Palm Door",
  "block.wilderwild.palm_fence": "Palm Fence",
  "block.wilderwild.palm_fence_gate": "Palm Fence Gate",
  "block.wilderwild.palm_fronds": "Palm Fronds",
  "block.wilderwild.palm_log": "Palm Log",
  "block.wilderwild.palm_crown": "Palmbaumkrone",
  "block.wilderwild.coconut": "Coconut",
  "block.wilderwild.palm_hanging_sign": "Palm Hanging Sign",
  "block.wilderwild.palm_planks": "Palm Planks",
  "block.wilderwild.palm_pressure_plate": "Palm Pressure Plate",
  "block.wilderwild.palm_sign": "Palm Sign",
  "block.wilderwild.palm_slab": "Palm Slab",
  "block.wilderwild.palm_stairs": "Palm Stairs",
  "block.wilderwild.palm_trapdoor": "Palm Trapdoor",
  "block.wilderwild.palm_wall_hanging_sign": "Palm Wall Hanging Sign",
  "block.wilderwild.palm_wall_sign": "Palm Wall Sign",
  "block.wilderwild.palm_wood": "Palm Wood",
  "block.wilderwild.pink_giant_glory_of_the_snow": "Rosaner Schneestolz",
  "block.wilderwild.pollen": "Pollen",
  "block.wilderwild.potted_baobab_nut": "Eingetopfte Baobab-Nuss",
  "block.wilderwild.potted_cypress_sapling": "Potted Cypress Sapling",
  "block.wilderwild.potted_coconut": "Eingetopfte Kokosnuss",
  "block.wilderwild.potted_carnation": "Potted Carnation",
  "block.wilderwild.potted_seeding_dandelion": "Potted Seeding Dandelion",
  "block.wilderwild.potted_prickly_big_dripleaf": "Potted Big Dripleaf",
  "block.wilderwild.potted_prickly_small_dripleaf": "Potted Small Dripleaf",
  "block.wilderwild.potted_bush": "Potted Bush",
  "block.wilderwild.potted_short_grass": "Getopftes kurzes Gras",
  "block.wilderwild.potted_tumbleweed_plant": "Potted Tumbleweed Stem",
  "block.wilderwild.potted_tumbleweed": "Potted Tumbleweed",
  "block.wilderwild.potted_prickly_pear": "Eingetopfte Kaktusfeige",
  "block.wilderwild.red_shelf_fungus": "Roter Porling",
  "block.wilderwild.scorched_sand": "Scorched Sand",
  "block.wilderwild.scorched_red_sand": "Scorched Red Sand",
  "block.wilderwild.sculk_slab": "Sculk Slab",
  "block.wilderwild.sculk_stairs": "Sculk Stairs",
  "block.wilderwild.sculk_wall": "Sculk Wall",
  "block.wilderwild.seeding_dandelion": "Seeding Dandelion",
  "block.wilderwild.stone_chest": "Steintruhe",
  "block.wilderwild.stripped_baobab_log": "Entrindeter Baobabstamm",
  "block.wilderwild.stripped_baobab_wood": "Entrindetes Baobabholz",
  "block.wilderwild.stripped_cypress_log": "Entrindeter Zypressenstamm",
  "block.wilderwild.stripped_cypress_wood": "Entrindetes Zypressenholz",
  "block.wilderwild.stripped_palm_log": "Entrindeter Palmenbaumstamm",
  "block.wilderwild.stripped_palm_wood": "Entrindetes Palmenbaumholz",
  "block.wilderwild.termite_mound": "Termite Mound",
  "block.wilderwild.violet_beauty_glory_of_the_snow": "Violetter Schneestolz",
  "block.wilderwild.blue_pearlescent_mesoglea": "Blue Pearlescent Mesoglea",
  "block.wilderwild.purple_pearlescent_mesoglea": "Purple Pearlescent Mesoglea",
  "block.wilderwild.red_mesoglea": "Rote Mesogloea",
  "block.wilderwild.blue_mesoglea": "Blaue Mesogloea",
  "block.wilderwild.yellow_mesoglea": "Gelbe Mesogloea",
  "block.wilderwild.lime_mesoglea": "Hellgrüne Mesogloea",
  "block.wilderwild.pink_mesoglea": "Rosa Mesogloea",
  "block.wilderwild.blue_pearlescent_nematocyst": "Blue Pearlescent Nematocyst",
  "block.wilderwild.purple_pearlescent_nematocyst": "Purple Pearlescent Nematocyst",
  "block.wilderwild.red_nematocyst": "Red Nematocyst",
  "block.wilderwild.blue_nematocyst": "Blue Nematocyst",
  "block.wilderwild.yellow_nematocyst": "Yellow Nematocyst",
  "block.wilderwild.lime_nematocyst": "Lime Nematocyst",
  "block.wilderwild.pink_nematocyst": "Pink Nematocyst",
  "block.wilderwild.tumbleweed_plant": "Tumbleweed Stem",
  "block.wilderwild.tumbleweed": "Tumbleweed",
  "block.wilderwild.small_sponge": "Kleiner Schwamm",
  "block.wilderwild.prickly_pear": "Kaktusfeige",
  "container.double_stone_chest": "Große Steintruhe",
  "container.stone_chest": "Steintruhe",
  "item.wilderwild.ancient_horn": "Antikes Horn",
  "item.wilderwild.ancient_horn.sound.0": "Whirs of the Ancient",
  "item.wilderwild.ancient_horn_fragment": "Ancient Horn Fragment",
  "item.wilderwild.baobab_boat": "Baobab Boat",
  "item.wilderwild.baobab_chest_boat": "Baobab Boat with Chest",
  "item.wilderwild.baobab_nut": "Baobabnuss",
  "item.wilderwild.black_firefly_bottle": "Schwarzes Glühwürmchen in einer Flasche",
  "item.wilderwild.blue_firefly_bottle": "Blaues Glühwürmchen in einer Flasche",
  "item.wilderwild.brown_firefly_bottle": "Braunes Glühwürmchen in einer Flasche",
  "item.wilderwild.camera": "Dev Camera",
  "item.wilderwild.copper_horn": "Kupferhorn",
  "item.wilderwild.crab_claw": "Crab Claw",
  "item.wilderwild.cooked_crab_claw": "Gekochte Krabbenschere",
  "item.minecraft.potion.effect.reach": "Trank des Erreichens",
  "item.minecraft.splash_potion.effect.reach": "Wurftrank des Erreichens",
  "item.minecraft.lingering_potion.effect.reach": "Verweiltrank des Erreichens",
  "item.minecraft.tipped_arrow.effect.reach": "Pfeil des Erreichens",
  "item.wilderwild.cyan_firefly_bottle": "Türkises Glühwürmchen in einer Flasche",
  "item.wilderwild.cypress_boat": "Cypress Boat",
  "item.wilderwild.cypress_chest_boat": "Cypress Boat with Chest",
  "item.wilderwild.palm_boat": "Palm Boat",
  "item.wilderwild.palm_chest_boat": "Palm Boat with Chest",
  "item.wilderwild.display_lantern": "Leere Schaukastenlaterne",
  "item.wilderwild.firefly_bottle": "Glühwürmchen in einer Flasche",
  "item.wilderwild.firefly_spawn_egg": "Firefly Spawn Egg",
  "item.wilderwild.gray_firefly_bottle": "Graues Glühwürmchen in einer Flasche",
  "item.wilderwild.green_firefly_bottle": "Grünes Glühwürmchen in einer Flasche",
  "item.wilderwild.jellyfish_spawn_egg": "Quallen-Spawn-Ei",
  "item.wilderwild.jellyfish_bucket": "Qualleneimer",
  "item.wilderwild.crab_spawn_egg": "Krabben-Spawn-Ei",
  "item.wilderwild.ostrich_spawn_egg": "Ostrich Spawn Egg",
  "item.wilderwild.crab_bucket": "Bucket of Crab",
  "item.wilderwild.light_blue_firefly_bottle": "Hellblaues Glühwürmchen in einer Flasche",
  "item.wilderwild.light_gray_firefly_bottle": "Hellgraues Glühwürmchen in einer Flasche",
  "item.wilderwild.lime_firefly_bottle": "Hellgrünes Glühwürmchen in einer Flasche",
  "item.wilderwild.magenta_firefly_bottle": "Magenta Glühwürmchen in einer Flasche",
  "item.wilderwild.milkweed_pod": "Seidenpflanzen-Balgfrucht",
  "item.wilderwild.orange_firefly_bottle": "Oranges Glühwürmchen in einer Flasche",
  "item.wilderwild.peeled_prickly_pear": "Peeled Prickly Pear",
  "item.wilderwild.pink_firefly_bottle": "Rosa Glühwürmchen in einer Flasche",
  "item.wilderwild.purple_firefly_bottle": "Violettes Glühwürmchen in einer Flasche",
  "item.wilderwild.red_firefly_bottle": "Rotes Glühwürmchen in einer Flasche",
  "item.wilderwild.white_firefly_bottle": "Weißes Glühwürmchen in einer Flasche",
  "item.wilderwild.yellow_firefly_bottle": "Gelbes Glühwürmchen in einer Flasche",
  "item.wilderwild.split_coconut": "Aufgebrochene Kokosnuss",
  "item.wilderwild.prickly_pear": "Kaktusfeige",
  "instrument.wilderwild.ancient_horn": "Whirs of the Ancient",
  "instrument.wilderwild.clarinet_copper_horn": "Klarinette",
  "instrument.wilderwild.flute_copper_horn": "Flöte",
  "instrument.wilderwild.oboe_copper_horn": "Oboe",
  "instrument.wilderwild.sax_copper_horn": "Saxophon",
  "instrument.wilderwild.trombone_copper_horn": "Posaune",
  "instrument.wilderwild.trumpet_copper_horn": "Trumpet",
  "instrument.wilderwild.tuba_copper_horn": "Tuba",
  "entity.wilderwild.ancient_horn_vibration": "Ancient Horn Vibration",
  "entity.wilderwild.baobab_boat": "Baobab Boat",
  "entity.wilderwild.baobab_chest_boat": "Baobab Boat with Chest",
  "entity.wilderwild.cypress_boat": "Cypress Boat",
  "entity.wilderwild.cypress_chest_boat": "Zypressenholztruhenboot",
  "entity.wilderwild.palm_boat": "Palm Boat",
  "entity.wilderwild.palm_chest_boat": "Palm Boat with Chest",
  "entity.wilderwild.firefly": "Firefly",
  "entity.wilderwild.jellyfish": "Qualle",
  "entity.wilderwild.crab": "Crab",
  "entity.wilderwild.tumbleweed": "Tumbleweed",
  "entity.wilderwild.ostrich": "Ostrich",
  "entity.wilderwild.coconut": "Coconut",
  "death.attack.ancient_horn": "%1$s was vaporized by a massive sound wave",
  "death.attack.ancient_horn.item": "%1$s was blown to smithereens by %2$s using %3$s",
  "death.attack.prickly_pear": "%1$s shoved spikes in their mouth",
  "death.attack.tumbleweed": "%1$s was tumbled",
  "death.attack.tumbleweed.item": "%1$s was tumbled by %2$s using %3$s",
  "death.attack.ostrich": "%1$s was pecked to death by %2$s",
  "death.attack.ostrich.item": "%1$s was pecked to death by %2$s wielding %3$s",
  "effect.wilderwild.reach_boost": "Reach Boost",
  "dataPack.wilderwild.update_1_21_additions.description": "\"Wilder Wild\"-Inhalte für Minecraft 1.20",
  "subtitles.block.hanging_tendril.wring": "Hanging Tendril wrung",
  "subtitles.block.sculk_sensor.hiccup": "Sculk Sensor hiccups",
  "subtitles.block.sculk_shrieker.gargle": "Sculk Shrieker gargles",
  "subtitles.block.hanging_tendril.clicking": "Hanging Tendril clicks",
  "subtitles.block.hanging_tendril.clicking_stop": "Hanging Tendril stops clicking",
  "subtitles.block.stone_chest.close_start": "Steindeckel senkt sich",
  "subtitles.block.stone_chest.item_crumble": "Ancient loot crumbles",
  "subtitles.block.stone_chest.lift": "Steindeckel hebt sich",
  "subtitles.block.stone_chest.open": "Stone Lid opened",
  "subtitles.block.stone_chest.slam": "Stone Lid slams",
  "subtitles.block.milkweed.rustle": "Milkweed rustled",
  "subtitles.block.termite_mound.termites": "Termiten schwärmen",
  "subtitles.block.termite_mound.termite_gnaw": "Termiten nagen",
  "subtitles.block.termite_mound.termite_gnaw_finish": "Termiten fressen",
  "subtitles.block.termite_mound.enter": "Termiten betreten Hügel",
  "subtitles.block.termite_mound.exit": "Termiten verlassen Hügel",
  "subtitles.block.tumbleweed.shear": "Tumbleweed cropped",
  "subtitles.block.prickly_pear.pick": "Kaktusfeige gepflückt",
  "subtitles.block.coconut.split": "Kokosnuss bricht",
  "subtitles.block.log_hollowed": "Axt höhlt aus",
  "subtitles.block.stem_hollowed": "Axt höhlt aus",
  "subtitles.block.ostrich_egg.crack": "Straußenei knackt",
  "subtitles.block.ostrich_egg.hatch": "Straußenei schlüpft",
  "subtitles.item.ancient_horn.call": "Antikes Horn spielt",
  "subtitles.item.bottle.catch_firefly": "Flasche füllt sich mit Glühwürmchen",
  "subtitles.item.bottle.put_in_lantern_firefly": "Glühwürmchen in Laterne platziert",
  "subtitles.item.bottle.release_firefly": "Glühwürmchen aus der Flasche freigelasssen",
  "subtitles.item.bucket.fill_jellyfish": "Qualle geschnappt",
  "subtitles.item.bucket.fill_crab": "Krabbe geschnappt",
  "subtitles.item.coconut.throw": "Kokosnuss geworfen",
  "subtitles.item.coconut.break": "Kokosnuss bricht",
  "subtitles.item.coconut.knock": "Coconut clunks",
  "subtitles.item.copper_horn.call": "Kupferhorn spielt",
  "subtitles.entity.ancient_horn_vibration.blast": "Ancient Horn Vibration blasts",
  "subtitles.entity.ancient_horn_vibration.flyby": "Ancient Horn Vibration flies by",
  "subtitles.entity.ancient_horn_vibration.dissipate": "Ancient Horn Vibration dissipates",
  "subtitles.entity.firefly.hide": "Firefly hides",
  "subtitles.entity.firefly.hurt": "Glühwürmchen zerdrückt",
  "subtitles.entity.firefly.nectar": "WE HAVE COME FOR YOUR NECTAR",
  "subtitles.entity.frog.sus_death": "Sussy frog dies L",
  "subtitles.entity.egg.land": "Egg splatters",
  "subtitles.entity.ender_pearl.land": "Ender Pearl shatters",
  "subtitles.entity.jellyfish.ambient": "Qualle gluckst",
  "subtitles.entity.jellyfish.whine": "Qualle heult",
  "subtitles.entity.jellyfish.swim": "Qualle schwimmt",
  "subtitles.entity.jellyfish.sting": "Qualle sticht",
  "subtitles.entity.jellyfish.hurt": "Qualle nimmt Schaden",
  "subtitles.entity.jellyfish.flop": "Qualle platscht",
  "subtitles.entity.jellyfish.death": "Qualle stirbt",
  "subtitles.entity.jellyfish.hide": "Qualle versteckt sich",
  "subtitles.entity.crab.idle": "Crab clatters",
  "subtitles.entity.crab.attack": "Crab snaps",
  "subtitles.entity.crab.hurt": "Crab hurts",
  "subtitles.entity.crab.death": "Crab dies",
  "subtitles.entity.crab.dig": "Krabbe gräbt",
  "subtitles.entity.crab.emerge": "Krabbe gräbt sich frei",
  "subtitles.entity.ostrich.idle": "Ostrich trills",
  "subtitles.entity.ostrich.grunt": "Strauße grunzt",
  "subtitles.entity.ostrich.hiss": "Strauß faucht",
  "subtitles.entity.ostrich.hurt": "Ostrich hurts",
  "subtitles.entity.ostrich.death": "Strauß stirbt",
  "subtitles.entity.ostrich.eat": "Strauß frisst",
  "subtitles.entity.ostrich.saddle": "Saddle equips",
  "subtitles.entity.ostrich.beak.stuck": "Strauß vergräbt Schnabel",
  "subtitles.entity.ostrich.beak.swing": "Strauß schwingt Hals",
  "subtitles.entity.ostrich.inbred.idle.ah": "Inbred Ostrich screams",
  "subtitles.entity.ostrich.inbred.idle.bock": "Inbred Ostrich thinks it's a chicken",
  "subtitles.entity.ostrich.inbred.hurt": "Inbred Ostrich shrieks in pain",
  "subtitles.entity.ostrich.inbred.death": "Inbred Ostrich rage quits",
  "subtitles.entity.ostrich.inbred.step": "Inbred Ostrich crunches its squishy feet",
  "subtitles.entity.ostrich.inbred.beak.stuck": "Inbred Ostrich beak",
  "subtitles.entity.ostrich.inbred.beak.swing": "Inbred Ostrich's creaky massive neck swings flirtatiously",
  "subtitles.entity.potion.magic": "Effect emanates",
  "subtitles.entity.potion.linger": "Effect lingers",
  "subtitles.entity.snowball.land": "Schneeball landet",
  "subtitles.entity.tumbleweed.move": "Tumbleweed tumbles",
  "subtitles.entity.tumbleweed.break": "Tumbleweed crumbles",
  "subtitles.entity.tumbleweed.damage": "Tumbleweed cracks",
  "subtitles.entity.warden.brap": "Warden stinks up the place",
  "subtitles.entity.warden.dying_underwater": "Wärter gluckst",
  "subtitles.entity.warden.stella_heartbeat": "Warden's heart ironically beats",
  "subtitles.entity.warden.swim": "Wärter schwimmt",
  "subtitles.particle.floating_sculk_bubble.big_pop": "Big Floating Sculk Bubble pops",
  "subtitles.particle.floating_sculk_bubble.pop": "Floating Sculk Bubble pops",
  "subtitles.particle.mesoglea_drip.land": "Mesoglea drips",
  "option.wilderwild.component.title": "\"Wilder Wild\"-Einstellungen",
  "option.wilderwild.block": "Block",
  "option.wilderwild.billboard_tendrils": "Billboard Hanging Tendrils",
  "tooltip.wilderwild.billboard_tendrils": "Whether Hanging Tendrils should use a billboard model\n(Flat plane that points at the camera.)",
  "option.wilderwild.tendrils_carry_events": "Hanging Tendrils Carry Events",
  "tooltip.wilderwild.tendrils_carry_events": "Whether Hanging Tendrils should retransmit game event context.\nWill allow Sculk Shriekers to be set off.",
  "option.wilderwild.shrieker_gargling": "Sculk-Kreischer-Gurgeln",
  "tooltip.wilderwild.shrieker_gargling": "Makes Sculk Shriekers 'gargle' when waterlogged.",
  "option.wilderwild.cactus_placement": "New Cactus Placement",
  "tooltip.wilderwild.cactus_placement": "Whether Cacti can be placed next to other blocks.\nIf you have Cactus farms, it is recommended you disable this.",
  "option.wilderwild.dripleaf_powering": "Dripleaf Powering",
  "tooltip.wilderwild.dripleaf_powering": "Whether Dripleaves will have a powered state and send Redstone power through their stems.",
  "option.wilderwild.frosted_ice_cracking": "New Frosted Ice Cracking",
  "tooltip.wilderwild.frosted_ice_cracking": "Whether Frosted Ice will spawn break particles and play a quiet break sound upon cracking.",
  "option.wilderwild.log_hollowing": "Stammaushöhlen",
  "tooltip.wilderwild.log_hollowing": "Ob Holzstämme mit Äxten ausgehöhlt werden können.\nKann bei der Kompatibilität mit anderen Mods helfen.",
  "option.wilderwild.mesoglea": "Mesogloea",
  "tooltip.wilderwild.mesoglea": "Enthält Einstellungen für Mesogloea.",
  "option.wilderwild.mesoglea_liquid": "Mesoglea Renders Like Liquid",
  "tooltip.wilderwild.mesoglea_liquid": "Whether Mesoglea will render like a liquid when waterlogged.",
  "option.wilderwild.mesoglea_bubble_columns": "Mesoglea Bubble Columns",
  "tooltip.wilderwild.mesoglea_bubble_columns": "Whether Mesoglea will be able to work as/with Bubble Columns.",
  "option.wilderwild.pollen_particles": "Pollenpartikel",
  "tooltip.wilderwild.pollen_particles": "Ob Pollenpartikel generiert werden sollen.\nKann die Leistung auf Geräten mit geringerer Rechenpower verbessern.",
  "option.wilderwild.soul_fire_sounds": "Seelenfeuergeräusche",
  "tooltip.wilderwild.soul_fire_sounds": "Sorgt dafür, dass Seelenfeuer eigene Umgebungsgeräusche erzeugen.",
  "option.wilderwild.stone_chest": "Steintruhe",
  "tooltip.wilderwild.stone_chest": "Enthält Einstellungen für die Steintruhe.",
  "option.wilderwild.stone_chest_timer": "Steintruhenöffnungsdauer",
  "tooltip.wilderwild.stone_chest_timer": "Bestimmt für wie lange die Steintruhe offen bleibt.\nDies ist eine Prozentzahl.",
  "option.wilderwild.termite": "Termite",
  "tooltip.wilderwild.termite": "Enthält Einstellungen für die Termiten.",
  "option.wilderwild.termites_only_eat_natural_blocks": "Nur natürliche Blöcke essen",
  "tooltip.wilderwild.termites_only_eat_natural_blocks": "Whether blocks placed by the player won't be eaten by Termites.\nDisable if this causes issues, as this adds a new property to some blocks.",
  "option.wilderwild.max_termite_distance": "Max Distance From Mound",
  "tooltip.wilderwild.max_termite_distance": "Controls how many blocks away from their Mound Termites can survive.",
  "option.wilderwild.max_natural_termite_distance": "Max Distance From Natural Mound",
  "tooltip.wilderwild.max_natural_termite_distance": "Controls how many blocks away from their Mound Termites can survive\nwhen the Mound was generated naturally.",
  "option.wilderwild.block_sounds": "Block Sounds",
  "tooltip.wilderwild.block_sounds": "Enthält Optionen, die Blockgeräusche überschreiben.",
  "option.wilderwild.cactus_sounds": "Kaktus-Soundeffekte",
  "tooltip.wilderwild.cactus_sounds": "Ob Soundeffekte für Kakteen überschrieben werden sollen.",
  "option.wilderwild.clay_sounds": "Ton(erde)-Soundeffekte",
  "tooltip.wilderwild.clay_sounds": "Ob Soundeffekte für Ton überschrieben werden sollen.",
  "option.wilderwild.coarse_dirt_sounds": "Grobe-Erde-Soundeffekte",
  "tooltip.wilderwild.coarse_dirt_sounds": "Ob Soundeffekte für rohe Erde überschrieben werden sollen.",
  "option.wilderwild.cobweb_sounds": "Spinnennetz-Soundeffekte",
  "tooltip.wilderwild.cobweb_sounds": "Ob Soundeffekte für Spinnweben überschrieben werden sollen.",
  "option.wilderwild.dead_bush_sounds": "Toter-Busch-Soundeffekte",
  "tooltip.wilderwild.dead_bush_sounds": "Ob Soundeffekte für toten Busch überschrieben werden sollen.",
  "option.wilderwild.flower_sounds": "Blumen-Soundeffekte",
  "tooltip.wilderwild.flower_sounds": "Ob Soundeffekte für Blumen überschrieben werden sollen.",
  "option.wilderwild.gravel_sounds": "Kies-Soundeffekte",
  "tooltip.wilderwild.gravel_sounds": "Ob Soundeffekte für Kies überschrieben werden sollen.",
  "option.wilderwild.ice_sounds": "Ice Sounds",
  "tooltip.wilderwild.ice_sounds": "Ob Soundeffekte für Eis überschrieben werden sollen.",
  "option.wilderwild.frosted_ice_sounds": "Brüchiges-Eis-Soundeffekte",
  "tooltip.wilderwild.frosted_ice_sounds": "Ob Soundeffekte für brüchiges Eis überschrieben werden sollen.",
  "option.wilderwild.leaf_sounds": "Laub-Soundeffekte",
  "tooltip.wilderwild.leaf_sounds": "Ob Soundeffekte für Laub überschrieben werden sollen.",
  "option.wilderwild.lily_pad_sounds": "Lily Pad Sounds",
  "tooltip.wilderwild.lily_pad_sounds": "Ob Soundeffekte für Seerosenblätter überschrieben werden sollen.",
  "option.wilderwild.mushroom_block_sounds": "Mushroom Block Sounds",
  "tooltip.wilderwild.mushroom_block_sounds": "Ob Soundeffekte für Pilzblöcke überschrieben werden sollen oder nicht.",
  "option.wilderwild.podzol_sounds": "Podsol-Soundeffekte",
  "tooltip.wilderwild.podzol_sounds": "Ob Soundeffekte für Podsol überschrieben werden sollen.",
  "option.wilderwild.sapling_sounds": "Setzling-Soundeffekte",
  "tooltip.wilderwild.sapling_sounds": "Ob Soundeffekte für Setzlinge überschrieben werden sollen.",
  "option.wilderwild.sugar_cane_sounds": "Zuckerrohr-Soundeffekte",
  "tooltip.wilderwild.sugar_cane_sounds": "Ob Soundeffekte für Zuckerrohr überschrieben werden sollen.",
  "option.wilderwild.reinforced_deepslate_sounds": "\"Verstärkter Tiefenschiefer\"-Soundeffekte",
  "tooltip.wilderwild.reinforced_deepslate_sounds": "Ob Soundeffekte für verstärkten Tiefenschiefer überschrieben werden sollen.",
  "option.wilderwild.wither_rose_sounds": "Wither-Rose-Soundeffekte",
  "tooltip.wilderwild.wither_rose_sounds": "Ob Soundeffekte für Wither-Rosen überschrieben werden sollen.",
  "option.wilderwild.sandstone_sounds": "Sandstein-Soundeffekte",
  "tooltip.wilderwild.sandstone_sounds": "Ob Soundeffekte für Sandstein überschrieben werden sollen.",
  "option.wilderwild.entity": "Entity",
  "option.wilderwild.allay": "Allay",
  "tooltip.wilderwild.allay": "Contains options for the Allay.",
  "option.wilderwild.keyframe_allay_dance": "Keyframe Allay Dancing",
  "tooltip.wilderwild.keyframe_allay_dance": "Whether the Allay's dancing animation should\nbe replaced with a keyframe-based version.",
  "option.wilderwild.crab": "Crab",
  "tooltip.wilderwild.crab": "Contains options for the Crab.",
  "option.wilderwild.crab_spawn_cap": "Crab Spawn Cap",
  "tooltip.wilderwild.crab_spawn_cap": "Controls the Crab's spawn cap.",
  "option.wilderwild.reach_affects_attack": "Reach Boost Affects Attack Range",
  "tooltip.wilderwild.reach_affects_attack": "Whether the Reach Boost effect will\nimpact the Player's attack range.",
  "option.wilderwild.enderman": "Enderman",
  "tooltip.wilderwild.enderman": "Contains options for the Enderman.",
  "option.wilderwild.anger_loop_sound": "Anger Loop Sound",
  "tooltip.wilderwild.anger_loop_sound": "Whether Endermen will start an anger sound loop when their target is set.",
  "option.wilderwild.moving_stare_sound": "Moving Stare Sound",
  "tooltip.wilderwild.moving_stare_sound": "Ob Enderman-Starr-Soundeffekte sich mit dem Enderman bewegen\nund ob sie frühzeitig gestoppt werden können.",
  "option.wilderwild.firefly": "Firefly",
  "tooltip.wilderwild.firefly": "Contains options for the Firefly.",
  "option.wilderwild.firefly_spawn_cap": "Firefly Spawn Cap",
  "tooltip.wilderwild.firefly_spawn_cap": "Controls the Firefly's spawn cap.",
  "option.wilderwild.jellyfish": "Qualle",
  "tooltip.wilderwild.jellyfish": "Contains options for the Jellyfish.",
  "option.wilderwild.jellyfish_spawn_cap": "Jellyfish Spawn Cap",
  "tooltip.wilderwild.jellyfish_spawn_cap": "Controls the Jellyfish's spawn cap.",
  "option.wilderwild.jellyfish_tentacles": "Quallententakel",
  "tooltip.wilderwild.jellyfish_tentacles": "Controls the amount of tentacles Jellyfish have.",
  "option.wilderwild.lightning": "Lightning Bolt",
  "tooltip.wilderwild.lightning": "Contains options for Lightning Bolts.",
  "option.wilderwild.lightning_scorches_sand": "Lightning Scorches Sand",
  "tooltip.wilderwild.lightning_scorches_sand": "Whether Lightning Bolts should scorch Sand blocks upon striking.",
  "option.wilderwild.lightning_block_particles": "Lightning Block Particles",
  "tooltip.wilderwild.lightning_block_particles": "Whether Lightning Bolts should spawn a stream of block particles upon striking.",
  "option.wilderwild.lightning_smoke_particles": "Lightning Smoke Particles",
  "tooltip.wilderwild.lightning_smoke_particles": "Whether Lightning Bolts should spawn smoke particles upon striking.",
  "option.wilderwild.ostrich": "Ostrich",
  "tooltip.wilderwild.ostrich": "Contains options for the Ostrich.",
  "option.wilderwild.spawn_ostriches": "Straußen spawnen",
  "tooltip.wilderwild.spawn_ostriches": "Whether Ostriches can spawn.",
  "option.wilderwild.allow_ostrich_attack": "Ostrich Peck Attack",
  "tooltip.wilderwild.allow_ostrich_attack": "Whether the Ostrich's peck attack can be used.",
  "option.wilderwild.tumbleweed": "Tumbleweed",
  "option.wilderwild.tumbleweed_spawn_cap": "Tumbleweed Spawn Cap",
  "tooltip.wilderwild.tumbleweed_spawn_cap": "Controls the Tumbleweed's spawn cap.",
  "option.wilderwild.leashed_tumbleweed": "Tumbleweed Leashing",
  "tooltip.wilderwild.leashed_tumbleweed": "Whether Tumbleweed are able to be leashed.",
  "tooltip.wilderwild.tumbleweed": "Contains options for the Tumbleweed.",
  "option.wilderwild.tumbleweed_destroys_crops": "Tumbleweed Destroys Crops",
  "tooltip.wilderwild.tumbleweed_destroys_crops": "Whether Tumbleweed can destroy crops.",
  "option.wilderwild.tumbleweed_rotates_to_look_direction": "Tumbleweed Rotates To Look Direction",
  "tooltip.wilderwild.tumbleweed_rotates_to_look_direction": "When enabled, Tumbleweed will rotate in the direction\nit's moving instead of spinning towards it.",
  "option.wilderwild.leashed_tumbleweed.false": "§cDisabled",
  "option.wilderwild.leashed_tumbleweed.true": "§aEnabled",
  "option.wilderwild.unpassable_rail": "Unpassable Rail",
  "tooltip.wilderwild.unpassable_rail": "Allows all mob entities to walk over rails instead of being unable to pass it.",
  "option.wilderwild.warden": "Wärter",
  "tooltip.wilderwild.warden": "Enthält Einstellungen für den Wärter.",
  "option.wilderwild.warden_attacks_immediately": "Der Wärter greift sofort an",
  "tooltip.wilderwild.warden_attacks_immediately": "Ob der Wärter bei Kontakt Kreaturen sofort angreift.",
  "option.wilderwild.warden_custom_tendrils": "Warden Tendril Animation",
  "tooltip.wilderwild.warden_custom_tendrils": "Vanilla: Warden's tendrils only rotate about a single axis.\nImproved: Warden's tendrils rotate about all axes, improving visibility from all angles.",
  "option.wilderwild.improved.false": "§cVanilla",
  "option.wilderwild.improved.true": "§aImproved",
  "option.wilderwild.warden_death_animation": "Todesanimation",
  "tooltip.wilderwild.warden_death_animation": "Ob der Wärter eine Animation haben sollte, wenn er stirbt.",
  "option.wilderwild.warden_emerges_from_command": "Warden Emerges from Command",
  "tooltip.wilderwild.warden_emerges_from_command": "Makes the Warden play the emerging animation when spawned via command.",
  "option.wilderwild.warden_emerges_from_egg": "Warden Emerges from Spawn Egg",
  "tooltip.wilderwild.warden_emerges_from_egg": "Makes the Warden play the emerging animation when spawned via spawn egg.",
  "option.wilderwild.warden_swims": "Wärter schwimmt",
  "tooltip.wilderwild.warden_swims": "Ob der Wärter schwimmen können sollte",
  "option.wilderwild.warden_swim_animation": "Wärter-Schwimm-Animation",
  "tooltip.wilderwild.warden_swim_animation": "Whether the Warden should §ovisually §rswim.\n§c(WARNING: Disabling this will cause the warden to appear to \nphase through blocks when swimming through one block tall gaps. \nPlease only disable this if it causes incompatibilities.)",
  "option.wilderwild.warden_bedrock_sniff": "Warden Sniff Animation",
  "tooltip.wilderwild.warden_bedrock_sniff": "Bedrock: Warden's head bobs thrice during the sniff animation\nJava: Warden's head bobs twice in the sniff animation",
  "option.wilderwild.warden_bedrock_sniff.false": "§cJava",
  "option.wilderwild.warden_bedrock_sniff.true": "§aBedrock",
  "option.wilderwild.warden_improved_dig": "Warden Dig Animation",
  "tooltip.wilderwild.warden_improved_dig": "Whether the Warden should use a slightly improved dig animation.",
  "option.wilderwild.warden_improved_emerge": "Warden Emerge Animation",
  "tooltip.wilderwild.warden_improved_emerge": "Whether the Warden should use a slightly improved emerge animation.",
  "option.wilderwild.item": "Item",
  "option.wilderwild.ancient_horn": "Antikes Horn",
  "tooltip.wilderwild.ancient_horn": "Contains options for the Ancient Horn.",
  "option.wilderwild.ancient_horn_can_summon_warden": "Ancient Horns Can Summon Wardens",
  "tooltip.wilderwild.ancient_horn_can_summon_warden": "Whether Ancient Horns should be able\nto summon Wardens from directly shooting Sculk Shriekers.",
  "option.wilderwild.ancient_horn_lifespan": "Ancient Horn Lifespan",
  "tooltip.wilderwild.ancient_horn_lifespan": "Amount of ticks before an Ancient Horn Vibration will despawn.",
  "option.wilderwild.ancient_horn_mob_damage": "Ancient Horn Mob Damage",
  "tooltip.wilderwild.ancient_horn_mob_damage": "Amount of damage the Ancient Horn will deal to non-player entities.",
  "option.wilderwild.ancient_horn_player_damage": "Ancient Horn Player Damage",
  "tooltip.wilderwild.ancient_horn_player_damage": "Amount of damage the Ancient Horn will deal to players.",
  "option.wilderwild.ancient_horn_shatters_glass": "Ancient Horn Glass Shattering",
  "tooltip.wilderwild.ancient_horn_shatters_glass": "Whether Glass blocks should break when shot with an Ancient Horn.\nEcho Glass will shatter regardless of this.",
  "option.wilderwild.ancient_horn_size_multiplier": "Ancient Horn Size Multiplier",
  "tooltip.wilderwild.ancient_horn_size_multiplier": "How much an Ancient Horn Vibration will increase in size by every tick.\nRecommended: 0.01.",
  "option.wilderwild.projectile_break_particles": "Landing Projectiles Emit Block Particles",
  "tooltip.wilderwild.projectile_break_particles": "Whether projectiles like Arrows or Tridents\nshould emit block breaking particles when colliding.",
  "option.wilderwild.projectile_landing_sounds": "Projektil-Lande-Soundeffekte",
  "tooltip.wilderwild.projectile_landing_sounds": "Enthält Einstellungen für das An- und Ausschalten von Soundeffekten, die beim Landen geworfener Projektile abgespielt werden.",
  "option.wilderwild.snowball_landing_sounds": "Schneeball-Lande-Soundeffekte",
  "tooltip.wilderwild.snowball_landing_sounds": "Ob für den Aufprall von Schneebällen eigene Soundeffekte abgespielt werden sollen.",
  "option.wilderwild.egg_landing_sounds": "Ei-Lande-Soundeffekte",
  "tooltip.wilderwild.egg_landing_sounds": "Ob für den Aufprall von Eiern eigene Soundeffekte abgespielt werden sollen.",
  "option.wilderwild.ender_pearl_landing_sounds": "Enderperlen-Lande-Soundeffekte",
  "tooltip.wilderwild.ender_pearl_landing_sounds": "Ob für den Aufprall von Enderperlen eigene Soundeffekte abgespielt werden sollen.",
  "option.wilderwild.potion_landing_sounds": "Trank-Lande-Soundeffekte",
  "tooltip.wilderwild.potion_landing_sounds": "Ob für den Aufprall von Tränken eigene Soundeffekte abgespielt werden sollen.\n(Soundeffekte variieren je nach Art des Trankes und seiner Wirkung.)",
  "option.wilderwild.restrict_instrument_sound": "Restrict Instrument Sounds",
  "tooltip.wilderwild.restrict_instrument_sound": "Whether instruments, such as the Goat Horn, should stop their sound when the user releases the mouse button",
  "option.wilderwild.worldgen": "Weltgeneration",
  "option.wilderwild.algae_generation": "Algengeneration",
  "tooltip.wilderwild.algae_generation": "Whether Algae is placed in worldgen.",
  "option.wilderwild.beta_beaches": "Beta Beaches",
  "tooltip.wilderwild.beta_beaches": "Ermöglicht Strände in der Nähe von Wasser, die unabhängig des Bioms generieren,\nähnlich der Generation von Stränden in der Minecraft Beta.",
  "option.wilderwild.bush_generation": "Buschgeneration",
  "tooltip.wilderwild.bush_generation": "Ob die Weltgeneration die Buschgeneration von Wilder Wild oder die Standard-Buschgenerierung verwenden soll.",
  "option.wilderwild.cactus_generation": "Kaktusgeneration",
  "tooltip.wilderwild.cactus_generation": "Ob die Weltgeneration die Kaktusgeneration von Wilder Wild oder die Standard-Kaktusgeneration verwenden soll.",
  "option.wilderwild.dying_trees": "Sterbende Bäume",
  "tooltip.wilderwild.dying_trees": "Ob sterbende Bäume in der Welt generieren sollen.",
  "option.wilderwild.fallen_trees": "Umgestürzte Bäume",
  "tooltip.wilderwild.fallen_trees": "Ob umgestürzte Bäume natürlich generiert werden.",
  "option.wilderwild.flower_generation": "Blumengeneration",
  "tooltip.wilderwild.flower_generation": "Ob die Weltgeneration die Blumengeneration von Wilder Wild oder die Standard-Blumengeneration verwenden soll.",
  "option.wilderwild.grass_generation": "Grasgeneration",
  "tooltip.wilderwild.grass_generation": "Ob die Weltgeneration die Grasgeneration von Wilder Wild oder die Standard-Grasgeneration verwenden soll.",
  "option.wilderwild.mushroom_generation": "Pilzgeneration",
  "tooltip.wilderwild.mushroom_generation": "Ob die Weltgeneration die Pilzgeneration von Wilder Wild oder die Standard-Pilzgeneration verwenden soll.",
  "option.wilderwild.new_witch_huts": "New Witch Huts",
  "tooltip.wilderwild.new_witch_huts": "Whether Witch Huts should use a Cypress and Mangrove wood set.",
  "option.wilderwild.snapped_trees": "Umgeknickte Bäume",
  "tooltip.wilderwild.snapped_trees": "Ob umgeknickte Bäume natürlich generiert werden.",
  "option.wilderwild.snow_below_trees": "Schnee und Eis unter Laub",
  "tooltip.wilderwild.snow_below_trees": "Ob die Weltgeneration Schnee und Eis unter Laub platzieren soll oder nicht.",
  "option.wilderwild.surface_decoration": "Surface Decoration",
  "tooltip.wilderwild.surface_decoration": "Whether Surface Decorators are placed in worldgen.\nThis includes things like Coarse Dirt and Packed Mud paths.",
  "option.wilderwild.surface_transitions": "Biome Surface Transitions",
  "tooltip.wilderwild.surface_transitions": "Whether unique biome surfaces should fizzle out in worldgen.",
  "option.wilderwild.termite_generation": "Termite Mound Generation",
  "tooltip.wilderwild.termite_generation": "Whether Termite Mounds are placed in worldgen.",
  "option.wilderwild.tree_generation": "Tree Generation",
  "tooltip.wilderwild.tree_generation": "Whether worldgen should use our custom tree types or the Vanilla tree types.",
  "option.wilderwild.tumbleweed_generation": "Tumbleweed Generation",
  "tooltip.wilderwild.tumbleweed_generation": "Whether Tumbleweed are placed in worldgen.",
  "option.wilderwild.biome_placement": "Biome Placement",
  "tooltip.wilderwild.biome_placement": "Contains options that change where biomes are placed into the world.",
  "option.wilderwild.modify_jungle_placement": "Jungle Placement",
  "tooltip.wilderwild.modify_jungle_placement": "Whether Jungles should use Wilder Wild's or Vanilla's placement.\nWilder Wild's placement replaces Deserts and Badlands with Jungles in humid areas.",
  "option.wilderwild.modify_mangrove_swamp_placement": "Mangrove Swamp Placement",
  "tooltip.wilderwild.modify_mangrove_swamp_placement": "Whether Mangrove Swamps should useWilder Wild's or Vanilla's placement.\nWilder Wild's placement doesn't place Mangrove Swamps in areas with low humidity.",
  "option.wilderwild.modify_swamp_placement": "Swamp Placement",
  "tooltip.wilderwild.modify_swamp_placement": "Whether Swamps should use Wilder Wild's or Vanilla's placement.\nWilder Wild's placement doesn't place Swamps in areas with low humidity.",
  "option.wilderwild.modify_windswept_savanna_placement": "Windswept Savanna Placement",
  "tooltip.wilderwild.modify_windswept_savanna_placement": "Whether Windswept Savannas should use Wilder Wild's or Vanilla's placement.\nWilder Wild's placement reduces the number of Windswept Savannas in cool areas.",
  "option.wilderwild.modify_cherry_grove_placement": "Cherry Grove Placement",
  "tooltip.wilderwild.modify_cherry_grove_placement": "Whether Cherry Groves should use Wilder Wild's or Vanilla's placement.\nWilder Wild's placement allows Cherry Groves to also generate near Rivers.",
  "option.wilderwild.modify_stony_shore_placement": "Stony Shore Placement",
  "tooltip.wilderwild.modify_stony_shore_placement": "Whether Stony Shores should use Wilder Wild's or Vanilla's placement.\nWilder Wild's placement replaces Beaches with Stony Shores when near Taigas.",
  "option.wilderwild.biome_placement.false": "§cVanilla",
  "option.wilderwild.biome_placement.true": "§aNeu",
  "option.wilderwild.biome_generation": "Biomgeneration",
  "tooltip.wilderwild.biome_generation": "Enthält Einstellungen, die bestimmen, ob Biome von Wilder Wild generiert werden sollen oder nicht.",
  "option.wilderwild.generate_cypress_wetlands": "Zypressensümpfe generieren",
  "tooltip.wilderwild.generate_cypress_wetlands": "Ob die Zypressensümpfe generiert werden sollen.",
  "option.wilderwild.generate_jellyfish_caves": "Quallenhöhlen generieren",
  "tooltip.wilderwild.generate_jellyfish_caves": "Ob Quallenhöhlen generiert werden sollen.",
  "option.wilderwild.generate_mixed_forest": "Mischwälder generieren",
  "tooltip.wilderwild.generate_mixed_forest": "Ob Mischwälder generiert werden sollen.",
  "option.wilderwild.generate_oasis": "Oasen generieren",
  "tooltip.wilderwild.generate_oasis": "Ob Oasen generiert werden sollen.",
  "option.wilderwild.generate_warm_river": "Warme Flüsse generieren",
  "tooltip.wilderwild.generate_warm_river": "Ob warme Flüsse generiert werden sollen.",
  "option.wilderwild.generate_warm_beach": "Warme Strände generieren",
  "tooltip.wilderwild.generate_warm_beach": "Ob warme Strände generiert werden sollen.",
  "option.wilderwild.generate_birch_taiga": "Birken-Taigas generieren",
  "tooltip.wilderwild.generate_birch_taiga": "Ob Birken-Taigas generiert werden sollen.",
  "option.wilderwild.generate_old_growth_birch_taiga": "Birken-Urtaigas generieren",
  "tooltip.wilderwild.generate_old_growth_birch_taiga": "Ob Birken-Urtaigas generiert werden sollen.",
  "option.wilderwild.generate_birch_jungle": "Birkendschungel generieren",
  "tooltip.wilderwild.generate_birch_jungle": "Ob Birkenwälder generiert werden sollen.",
  "option.wilderwild.generate_sparse_birch_jungle": "Karger Birkendschungel generieren",
  "tooltip.wilderwild.generate_sparse_birch_jungle": "Ob karge Birkendschungel generiert werden sollen.",
  "option.wilderwild.generate_flower_field": "Blumenfelder generieren",
  "tooltip.wilderwild.generate_flower_field": "Ob Blumenfelder generiert werden sollen.",
  "option.wilderwild.generate_arid_savanna": "Trockensavannen generieren",
  "tooltip.wilderwild.generate_arid_savanna": "Ob Trockensavannen generiert werden sollen.",
  "option.wilderwild.generate_parched_forest": "Ausgedorrte Wälder generieren",
  "tooltip.wilderwild.generate_parched_forest": "Ob ausgedorrte Wälder generiert werden sollen.",
  "option.wilderwild.generate_arid_forest": "Trockenwälder  generieren",
  "tooltip.wilderwild.generate_arid_forest": "Ob Trockenwälder generiert werden sollen.",
  "option.wilderwild.generate_snowy_old_growth_pine_taiga": "Generiere verschneite Kiefern-Urtaigas",
  "tooltip.wilderwild.generate_snowy_old_growth_pine_taiga": "Ob verschneite Kiefern-Urtaigas generiert werden sollen.",
  "option.wilderwild.generate_old_growth_dark_forest": "Generiere Dunkle Urwälder",
  "tooltip.wilderwild.generate_old_growth_dark_forest": "Ob dunkle Urwälder generiert werden sollen.",
  "option.wilderwild.generate_dark_birch_forest": "Dunkle Birkenwälder generieren",
  "tooltip.wilderwild.generate_dark_birch_forest": "Ob dunkle Birkenwälder generiert werden sollen.",
  "option.wilderwild.generate_semi_birch_forest": "Generate Semi Birch Forests",
  "tooltip.wilderwild.generate_semi_birch_forest": "Whether Semi Birch Forests should generate.",
  "option.wilderwild.generate_temperate_rainforest": "Gemäßigte Regenwälder generieren",
  "tooltip.wilderwild.generate_temperate_rainforest": "Ob gemäßigte Regenwälder generiert werden sollen.",
  "option.wilderwild.generate_rainforest": "Regenwälder generieren",
  "tooltip.wilderwild.generate_rainforest": "Ob Regenwälder generiert werden sollen.",
  "option.wilderwild.generate_dark_taiga": "Dunkle Taigas generieren",
  "tooltip.wilderwild.generate_dark_taiga": "Ob Dunkle Taigas generiert werden sollen.",
  "option.wilderwild.generate_dying_forest": "Sterbende Wälder generieren",
  "tooltip.wilderwild.generate_dying_forest": "Ob sterbende Wälder generiert werden sollen.",
  "option.wilderwild.generate_snowy_dying_forest": "Generiere verschneite sterbende Wälder",
  "option.wilderwild.generate_dying_mixed_forest": "Sterbende Mischwälder generieren",
  "tooltip.wilderwild.generate_snowy_dying_forest": "Ob schneebedeckte sterbende Wälder generiert werden sollen.",
  "tooltip.wilderwild.generate_dying_mixed_forest": "Ob sterbende Mischwälder generiert werden sollen.",
  "option.wilderwild.generate_snowy_dying_mixed_forest": "Generiere verschneite sterbende Mischwälder",
  "tooltip.wilderwild.generate_snowy_dying_mixed_forest": "Ob schneebedeckte sterbende Mischwälder generiert werden sollen.",
  "option.wilderwild.biome.false": "§cDisabled",
  "option.wilderwild.biome.true": "§aEnabled",
  "option.wilderwild.misc": "Misc",
  "option.wilderwild.biome_ambience": "Biom-Atmosphäre",
  "tooltip.wilderwild.biome_ambience": "Enthält Einstellungen für die Geräuschkulisse des Bioms.",
  "option.wilderwild.deep_dark_ambience": "Tiefes-Dunkel-Ambiente",
  "tooltip.wilderwild.deep_dark_ambience": "Ob die neuen Ambientgeräusche des\nTiefes-Dunkel-Bioms verwendet werden sollen.",
  "option.wilderwild.dripstone_caves_ambience": "Tropfsteinhöhlen-Ambiente",
  "tooltip.wilderwild.dripstone_caves_ambience": "Ob die neuen Ambientgeräusche des\nTropfsteinhöhlen-Bioms verwendet werden sollen.",
  "option.wilderwild.lush_caves_ambience": "Üppige-Höhlen-Ambiente",
  "tooltip.wilderwild.lush_caves_ambience": "Ob die neuen Ambientgeräusche des\nÜppige-Höhlen-Bioms verwendet werden sollen.",
  "option.wilderwild.biome_music": "Biom-Musik",
  "tooltip.wilderwild.biome_music": "Enthält Einstellungen für Biom-Musik.",
  "option.wilderwild.cloud_movement": "Wolkenbewegung",
  "tooltip.wilderwild.cloud_movement": "Ob Wolken sich einem Windsystem folgend fortbewegen sollten.",
  "option.wilderwild.firework_wind_movement": "Firework Rocket Wind Intensity",
  "tooltip.wilderwild.firework_wind_movement": "Controls the intensity of wind on Firework Rockets.\nThis is a percentage.",
  "option.wilderwild.item_cooldowns_save": "Item Cooldowns Save",
  "tooltip.wilderwild.item_cooldowns_save": "Whether item cooldowns will save instead of being\ncleared upon switching dimensions or rejoining a world.",
  "option.wilderwild.modify_advancements": "Modify Advancements",
  "tooltip.wilderwild.modify_advancements": "Whether advancements should contain Wilder Wild's criteria.\nDisable this if it causes compatability issues.",
  "option.wilderwild.particle_wind_movement": "Particle Wind Intensity",
  "tooltip.wilderwild.particle_wind_movement": "Controls the intensity of wind on affected particles.\nThis is a percentage.",
  "option.wilderwild.water_colors": "Gewässerfärbung",
  "tooltip.wilderwild.water_colors": "Enthält Einstellungen, die die Gewässerfärbung eines jeweiligen Bioms an seine Temperatur anpassen.",
  "option.wilderwild.frozen_water": "Vereiste und eisige Gewässer",
  "tooltip.wilderwild.frozen_water": "Ob vereiste und eisige Biome die Gewässerfärbung von Wilder Wild oder die Standardfarben verwenden sollen.",
  "option.wilderwild.snowy_water": "Verschneite Gewässer",
  "tooltip.wilderwild.snowy_water": "Ob verschneite Biome die Gewässerfärbung von Wilder Wild oder die Standardfarben verwenden sollen.",
  "option.wilderwild.lukewarm_water": "Lauwarme Gewässer",
  "tooltip.wilderwild.lukewarm_water": "Ob lauwarme Biome die Gewässerfärbung von Wilder Wild oder die Standardfarben verwenden sollen.",
  "option.wilderwild.hot_water": "Warme Gewässer",
  "tooltip.wilderwild.hot_water": "Ob warme Biome die Gewässerfärbung von Wilder Wild oder die Standardfarben verwenden sollen.",
  "option.wilderwild.water_colors.false": "§cVanilla",
  "option.wilderwild.water_colors.true": "§aNeu",
  "option.wilderwild.wilder_forest_music": "\"Wilder\" Musik in Wäldern",
  "tooltip.wilderwild.wilder_forest_music": "Ob in einigen waldartigen Biomen neue Musik verwendet werden soll.",
  "option.wilderwild.simple_bool.false": "§cOFF",
  "option.wilderwild.simple_bool.true": "§aON",
  "wilderwild.advancements.adventure.use_ancient_horn.title": "Whirs of the Ancient",
  "wilderwild.advancements.adventure.use_ancient_horn.description": "Craft and use an Ancient Horn",
  "wilderwild.advancements.adventure.obtain_null_block.title": "Hackermodus = §aAN",
  "wilderwild.advancements.adventure.obtain_null_block.description": "Obtain a Null Block",
  "wilderwild.advancements.husbandry.firefly_in_a_bottle.title": "Blitz in der Flasche",
  "wilderwild.advancements.husbandry.firefly_in_a_bottle.description": "Fange ein Glühwürmchen in einer Flasche",
  "wilderwild.advancements.husbandry.jellyfish_in_a_bucket.title": "Stich!",
  "wilderwild.advancements.husbandry.jellyfish_in_a_bucket.description": "Fange eine Qualle in einem Eimer",
  "wilderwild.advancements.husbandry.crab_in_a_bucket.title": "Crabby Road",
  "wilderwild.advancements.husbandry.crab_in_a_bucket.description": "Fange einen Krabbe in einem Eimer",
  "commands.sculkspread.success": "Spread Sculk at %s, %s, %s with a charge of %s.",
  "commands.sculkspread.worldgen.success": "Spread Worldgen Sculk at %s, %s, %s with a charge of %s."
}
