{
    "cosmetic.snownee.2020q3": "",
    "cosmetic.snownee.2020q4": "",
    "cosmetic.snownee.2021q1": "",
    "cosmetic.snownee.sunny_milk": "",
    "cosmetic.snownee.xmas": "",
    "gui.kiwi.cosmetic": "",
    "item.kiwi.first_item.tip": "",
    "item.kiwi.first_item.tip.shift": "",
    "kiwi.config.client": "",
    "kiwi.config.common": "",
    "kiwi.config.debug": "",
    "kiwi.config.debug.NBTTooltip": "",
    "kiwi.config.debug.NBTTooltip.desc": "",
    "kiwi.config.debug.tagsTooltip": "",
    "kiwi.config.debug.tagsTooltip.desc": "",
    "kiwi.config.globalTooltip": "",
    "kiwi.config.globalTooltip.desc": "",
    "kiwi.config.modules": "",
    "kiwi.config.noMicrosoftTelemetry": "",
    "kiwi.config.noMicrosoftTelemetry.desc": "",
    "kiwi.config.requiresRestart": "",
    "kiwi.config.server": "",
    "kiwi.config.suppressExperimentalSettingsWarning": "",
    "kiwi.config.suppressExperimentalSettingsWarning.desc": "",
    "modmenu.descriptionTranslation.kiwi": "",
    "modmenu.nameTranslation.kiwi": "",
    "msg.kiwi.no_dependencies": "",
    "tip.kiwi.click_here": "",
    "tip.kiwi.debug_tooltip": "",
    "tip.kiwi.debug_tooltip.success": "",
    "tip.kiwi.press_ctrl": "",
    "tip.kiwi.press_shift": "",
    "tip.kiwi.press_shift_or_ctrl": ""
}