{
  "item.pureberries.goji_berry_tart": "Goji Berry Tart",
  "block.sweetberryfoods.cloudberry_plant_3": "Cloudberry Plant 3",
  "block.pureberries.blueberry_bush_plant_stage_2": "Blueberry Bush",
  "block.pureberries.blueberry_bush_plant_stage_3": "Blueberry Bush",
  "item.pureberries.goji_berries_cooked": "Cooked Goji Berries",
  "block.pureberries.blueberry_bush_plant_stage_0": "Blueberry Bush",
  "item.pureberries.blueberries": "Blueberries",
  "item.pureberries.goji_berry_biscuit": "Goji Berry Biscuit",
  "block.pureberries.blueberry_bush_plant_stage_1": "Blueberry Bush",
  "item.pureberries.goji_berry_jam": "Goji Berry Jam",
  "item.sweetberryfoods.cooked_blueberries": "Cooked Blueberries",
  "advancements.adv_give_sweet_berry_recipes.title": "Adv Give Sweet Berry Recipes",
  "block.pureberries.goji_berry_bush_stage_0": "Goji Berry Bush",
  "block.pureberries.blueberry_bush_stage_1": "Blueberry Bush",
  "block.pureberries.goji_berry_bush_stage_1": "Goji Berry Bush",
  "block.pureberries.blueberry_bush_stage_0": "Blueberry Bush",
  "item.pureberries.glow_berry_biscuit": "Glow Berry Biscuit",
  "item.pureberries.blueberry_biscuit": "Blueberry Biscuit",
  "block.pureberries.goji_berry_bush_stage_6": "Goji Berry Bush",
  "block.pureberries.goji_berry_bush_stage_7": "Goji Berry Bush",
  "block.pureberries.goji_berry_bush_stage_4": "Goji Berry Bush",
  "block.pureberries.goji_berry_bush_stage_5": "Goji Berry Bush",
  "item.pureberries.cloudberry_biscuit": "Cloudberry Biscuit",
  "block.pureberries.goji_berry_bush_stage_2": "Goji Berry Bush",
  "item.pureberries.blueberry_jam": "Blueberry Jam",
  "block.pureberries.goji_berry_bush_stage_3": "Goji Berry Bush",
  "item.sweetberryfoods.honey_dipped_sweet_berries": "Honey Dipped Sweet Berries",
  "item.sweetberryfoods.blueberry_jam_sandwich": "Blueberry Jam Sandwich",
  "item.pureberries.sweet_berry_jam_sandwich": "Sweet Berry Jam Sandwich",
  "item.pureberries.goji_berry_juice": "Goji Berry Juice",
  "item.pureberries.cloudberry_jam_sandwich": "Cloudberry Jam Sandwich",
  "advancements.adv_give_cloudberry_recipes.descr": "Adv Give Cloudberry Recipes",
  "item.sweetberryfoods.sweet_berry_jam": "Sweet Berry Jam",
  "item.pureberries.cloudberry_jam": "Cloudberry Jam",
  "block.pureberries.blueberry_bush_stage_3": "Blueberry Bush",
  "block.pureberries.blueberry_bush_stage_2": "Blueberry Bush",
  "item.sweetberryfoods.blueberry_biscuit": "Blueberry Biscuit",
  "item.pureberries.sweet_berries_cocoa_covered": "Cocoa Covered Sweet Berries",
  "item.pureberries.sweet_berry_juice": "Sweet Berry Juice",
  "item.sweetberryfoods.blueberry_juice": "Blueberry Juice",
  "item.pureberries.glow_berries_honey_dipped": "Honey Dipped Glow Berries",
  "item.sweetberryfoods.cocoa_covered_blueberries": "Cocoa Covered Blueberries",
  "advancements.adv_give_cloudberry_recipes.title": "Adv Give Cloudberry Recipes",
  "item.pureberries.cloudberries_cocoa_covered": "Cocoa Covered Cloudberries",
  "item.pureberries.goji_berries_cocoa_covered": "Cocoa Covered Goji Berries",
  "item.sweetberryfoods.blueberries": "Blueberries",
  "block.sweetberryfoods.blueberry_bush_plant_stage_0": "Blueberry Bush",
  "block.sweetberryfoods.blueberry_bush_plant_stage_2": "Blueberry Bush",
  "block.sweetberryfoods.blueberry_bush_plant_stage_1": "Blueberry Bush",
  "block.sweetberryfoods.blueberry_bush_plant_stage_3": "Blueberry Bush",
  "advancements.adv_give_goji_berry_recipes.title": "Adv Give Goji Berry Recipes",
  "item.pureberries.glow_berry_jam": "Glow Berry Jam",
  "item.sweetberryfoods.sweet_berry_juice": "Sweet Berry Juice",
  "item.pureberries.glow_berry_tart": "Glow Berry Tart",
  "item.pureberries.goji_berry_muffin": "Goji Berry Muffin",
  "advancements.adv_give_blueberry_recipes.title": "Adv Give Blueberry Recipes",
  "item.pureberries.sweet_berry_biscuit": "Sweet Berry Biscuit",
  "item.sweetberryfoods.sweet_berry_muffin": "Sweet Berry Muffin",
  "item.pureberries.glow_berry_muffin": "Glow Berry Muffin",
  "item.pureberries.cloudberry_juice": "Cloudberry Juice",
  "item.sweetberryfoods.honey_dipped_blueberries": "Honey Dipped Blueberries",
  "item.pureberries.cloudberry_muffin": "Cloudberry Muffin",
  "item.pureberries.blueberry_tart": "Blueberry Tart",
  "item.sweetberryfoods.cloudberry": "Cloudberry",
  "item.pureberries.sweet_berries_honey_dipped": "Honey Dipped Sweet Berries",
  "item.pureberries.blueberries_honey_dipped": "Honey Dipped Blueberries",
  "item.sweetberryfoods.sweet_berry_biscuit": "Sweet Berry Biscuit",
  "item.sweetberryfoods.blueberry_tart": "Blueberry Tart",
  "advancements.adv_give_blueberry_recipes.descr": "Adv Give Blueberry Recipes",
  "item.pureberries.sweet_berries_cooked": "Cooked Sweet Berries",
  "effect.pureberries.fortified_eyes": "Fortified Eyes",
  "item.pureberries.glow_berries_cocoa_covered": "Cocoa Covered Glow Berries",
  "item.pureberries.cloudberry_tart": "Cloudberry Tart",
  "item.pureberries.blueberry_jam_sandwich": "Blueberry Jam Sandwich",
  "item.sweetberryfoods.cocoa_covered_sweet_berries": "Cocoa Covered Sweet Berries",
  "item.sweetberryfoods.sweet_berry_jam_sandwich": "Sweet Berry Jam Sandwich",
  "item.pureberries.blueberries_cocoa_covered": "Cocoa Covered Blueberries",
  "block.pureberries.cloudberry_plant_stage_1": "Cloudberry Plant",
  "item.pureberries.cloudberries": "Cloudberries",
  "block.pureberries.cloudberry_plant_stage_0": "Cloudberry Plant",
  "block.pureberries.cloudberry_plant_stage_3": "Cloudberry Plant",
  "block.pureberries.cloudberry_plant_stage_2": "Cloudberry Plant",
  "item.pureberries.glow_berry_juice": "Glow Berry Juice",
  "item.sweetberryfoods.blueberry_jam": "Blueberry Jam",
  "item.sweetberryfoods.cooked_sweet_berries": "Cooked Sweet Berries",
  "item.pureberries.cloudberries_honey_dipped": "Honey Dipped Cloudberries",
  "advancements.adv_give_glow_berry_recipes.title": "Adv Give Glow Berry Recipes",
  "item.pureberries.sweet_berry_jam": "Sweet Berry Jam",
  "item.pureberries.goji_berry_jam_sandwich": "Goji Berry Jam Sandwich",
  "advancements.adv_give_goji_berry_recipes.descr": "Adv Give Goji Berry Recipes",
  "item.pureberries.blueberry_muffin": "Blueberry Muffin",
  "item.pureberries.blueberry_juice": "Blueberry Juice",
  "item.pureberries.sweet_berry_tart": "Sweet Berry Tart",
  "item.pureberries.cloudberries_cooked": "Cooked Cloudberries",
  "item.pureberries.sweet_berry_muffin": "Sweet Berry Muffin",
  "item.pureberries.goji_berries": "Goji Berry",
  "item.pureberries.goji_berries_honey_dipped": "Honey Dipped Goji Berries",
  "item.pureberries.glow_berries_cooked": "Cooked Glow Berries",
  "item.pureberries.blueberries_cooked": "Cooked Blueberries",
  "advancements.adv_give_glow_berry_recipes.descr": "Adv Give Glow Berry Recipes",
  "advancements.adv_give_sweet_berry_recipes.descr": "Adv Give Sweet Berry Recipes",
  "item.pureberries.glow_berry_jam_sandwich": "Glow Berry Jam Sandwich",
  "item.sweetberryfoods.sweet_berry_tart": "Sweet Berry Tart",
  "item.sweetberryfoods.blueberry_muffin": "Blueberry Muffin"
}