{
    "block.consistency_plus.copper_brick_gate": "Kupferziegeltor",
    "block.consistency_plus.copper_brick_slab": "Kupferziegelstufe",
    "block.consistency_plus.copper_brick_stairs": "Kupferziegeltreppe",
    "block.consistency_plus.copper_brick_wall": "Kupferziegelmauer",
    "block.consistency_plus.copper_bricks": "Kupferziegel",
    "block.consistency_plus.copper_gate": "Kupfertor",
    "block.consistency_plus.copper_pillar": "Kupfersäule",
    "block.consistency_plus.copper_slab": "Kupferstufe",
    "block.consistency_plus.copper_stairs": "Kupfertreppe",
    "block.consistency_plus.copper_tile_gate": "Kupferfliesentor",
    "block.consistency_plus.copper_tile_wall": "Kupferfliesenmauer",
    "block.consistency_plus.copper_wall": "Kupfermauer",
    "block.consistency_plus.cut_copper_gate": "Geschnittenes Kupfertor",
    "block.consistency_plus.cut_copper_wall": "Geschnittene Kupfermauer",
    "block.consistency_plus.exposed_copper_brick_gate": "Angelaufenes Kupferziegeltor",
    "block.consistency_plus.exposed_copper_brick_slab": "Angelaufene Kupferziegelstufe",
    "block.consistency_plus.exposed_copper_brick_stairs": "Angelaufene Kupferziegeltreppe",
    "block.consistency_plus.exposed_copper_brick_wall": "Angelaufene Kupferziegelmauer",
    "block.consistency_plus.exposed_copper_bricks": "Angelaufene Kupferziegel",
    "block.consistency_plus.exposed_copper_gate": "Angelaufenes Kupfertor",
    "block.consistency_plus.exposed_copper_pillar": "Angelaufene Kupfersäule",
    "block.consistency_plus.exposed_copper_slab": "Angelaufene Kupferstufe",
    "block.consistency_plus.exposed_copper_stairs": "Angelaufene Kupfertreppe",
    "block.consistency_plus.exposed_copper_tile_gate": "Angelaufenes Kupferfliesentor",
    "block.consistency_plus.exposed_copper_tile_wall": "Angelaufene Kupferfliesenmauer",
    "block.consistency_plus.exposed_copper_wall": "Angelaufene Kupfermauer",
    "block.consistency_plus.exposed_cut_copper_gate": "Angelaufenes geschnittenes Kupfertor",
    "block.consistency_plus.exposed_cut_copper_wall": "Angelaufene geschnittene Kupfermauer",
    "block.consistency_plus.exposed_smooth_copper": "Angelaufenes glattes Kupfer",
    "block.consistency_plus.exposed_smooth_copper_gate": "Angelaufenes glattes Kupfertor",
    "block.consistency_plus.exposed_smooth_copper_slab": "Angelaufene glatte Kupferstufe",
    "block.consistency_plus.exposed_smooth_copper_stairs": "Angelaufene glatte Kupfertreppe",
    "block.consistency_plus.exposed_smooth_copper_wall": "Angelaufene glatte Kupferwand",
    "block.consistency_plus.oxidized_copper_brick_gate": "Oxidiertes Kupferziegeltor",
    "block.consistency_plus.oxidized_copper_brick_slab": "Oxidierte Kupferziegelstufe",
    "block.consistency_plus.oxidized_copper_brick_stairs": "Oxidierte Kupferziegeltreppe",
    "block.consistency_plus.oxidized_copper_brick_wall": "Oxidierte Kupferziegelmauer",
    "block.consistency_plus.oxidized_copper_bricks": "Oxidierte Kupferziegel",
    "block.consistency_plus.oxidized_copper_pillar": "Oxidierte Kupfersäule",
    "block.consistency_plus.oxidized_copper_slab": "Oxidierte Kupferstufe",
    "block.consistency_plus.oxidized_copper_stairs": "Oxidierte Kupfertreppe",
    "block.consistency_plus.oxidized_copper_tile_gate": "Oxidiertes Kupferfliesentor",
    "block.consistency_plus.oxidized_copper_tile_wall": "Oxidierte Kupferfliesenmauer",
    "block.consistency_plus.oxidized_copper_wall": "Oxidierte Kupfermauer",
    "block.consistency_plus.oxidized_cut_copper_gate": "Oxidiertes geschnittenes Kupfertor",
    "block.consistency_plus.oxidized_cut_copper_wall": "Oxidierte geschnittene Kupfermauer",
    "block.consistency_plus.oxidized_smooth_copper": "Oxidiertes glattes Kupfer",
    "block.consistency_plus.oxidized_smooth_copper_gate": "Oxidiertes glattes Kupfertor",
    "block.consistency_plus.oxidized_smooth_copper_slab": "Oxidierte glatte Kupferstufe",
    "block.consistency_plus.oxidized_smooth_copper_stairs": "Oxidierte glatte Kupfertreppe",
    "block.consistency_plus.oxidized_smooth_copper_wall": "Oxidierte glatte Kupferwand",
    "block.consistency_plus.polished_copper_gate": "Poliertes Kupfertor",
    "block.consistency_plus.smooth_copper": "Glattes Kupfer",
    "block.consistency_plus.smooth_copper_gate": "Glattes Kupfertor",
    "block.consistency_plus.smooth_copper_slab": "Glatte Kupferstufe",
    "block.consistency_plus.smooth_copper_stairs": "Glatte Kupfertreppe",
    "block.consistency_plus.smooth_copper_wall": "Glatte Kupferwand",
    "block.consistency_plus.waxed_copper_brick_gate": "Gewachstes Kupferziegeltor",
    "block.consistency_plus.waxed_copper_brick_slab": "Gewachste Kupferziegelstufe",
    "block.consistency_plus.waxed_copper_brick_stairs": "Gewachste Kupferziegeltreppe",
    "block.consistency_plus.waxed_copper_brick_wall": "Gewachste Kupferziegelmauer",
    "block.consistency_plus.waxed_copper_bricks": "Gewachste Kupferziegel",
    "block.consistency_plus.waxed_copper_gate": "Gewachstes Kupfertor",
    "block.consistency_plus.waxed_copper_pillar": "Gewachste Kupfersäule",
    "block.consistency_plus.waxed_copper_slab": "Gewachste Kupferstufe",
    "block.consistency_plus.waxed_copper_stairs": "Gewachste Kupfertreppe",
    "block.consistency_plus.waxed_copper_tile_gate": "Gewachstes Kupferfliesentor",
    "block.consistency_plus.waxed_copper_tile_wall": "Gewachste Kupferfliesenmauer",
    "block.consistency_plus.waxed_copper_wall": "Gewachste Kupfermauer",
    "block.consistency_plus.waxed_cut_copper_gate": "Gewachstes geschnittenes Kupfertor",
    "block.consistency_plus.waxed_cut_copper_wall": "Gewachste geschnittene Kupfermauer",
    "block.consistency_plus.waxed_exposed_copper_brick_gate": "Gewachstes angelaufenes Kupferziegeltor",
    "block.consistency_plus.waxed_exposed_copper_brick_slab": "Gewachste angelaufene Kupferziegelstufe",
    "block.consistency_plus.waxed_exposed_copper_brick_stairs": "Gewachste angelaufene Kupferziegeltreppe",
    "block.consistency_plus.waxed_exposed_copper_brick_wall": "Gewachste angelaufene Kupferziegelmauer",
    "block.consistency_plus.waxed_exposed_copper_bricks": "Gewachste angelaufene Kupferziegel",
    "block.consistency_plus.waxed_exposed_copper_pillar": "Gewachste angelaufene Kupfersäule",
    "block.consistency_plus.waxed_exposed_copper_slab": "Gewachste angelaufene Kupferstufe",
    "block.consistency_plus.waxed_exposed_copper_stairs": "Gewachste angelaufene Kupfertreppe",
    "block.consistency_plus.waxed_exposed_copper_tile_gate": "Gewachstes angelaufenes Kupferfliesentor",
    "block.consistency_plus.waxed_exposed_copper_tile_wall": "Gewachste angelaufene Kupferfliesenmauer",
    "block.consistency_plus.waxed_exposed_copper_wall": "Gewachstes angelaufenes Kupfermauer",
    "block.consistency_plus.waxed_exposed_cut_copper_gate": "Gewachstes angelaufenes geschnittenes Kupfertor",
    "block.consistency_plus.waxed_exposed_cut_copper_wall": "Gewachste angelaufene geschnittene Kupfermauer",
    "block.consistency_plus.waxed_exposed_smooth_copper": "Gewachstes angelaufenes glattes Kupfer",
    "block.consistency_plus.waxed_exposed_smooth_copper_gate": "Gewachstes angelaufenes glattes Kupfertor",
    "block.consistency_plus.waxed_exposed_smooth_copper_slab": "Gewachste angelaufene glatte Kupferstufe",
    "block.consistency_plus.waxed_exposed_smooth_copper_stairs": "Gewachste angelaufene glatte Kupfertreppe",
    "block.consistency_plus.waxed_exposed_smooth_copper_wall": "Gewachste angelaufene glatte Kupferwand",
    "block.consistency_plus.waxed_oxidized_copper_brick_gate": "Gewachstes oxidiertes Kupferziegeltor",
    "block.consistency_plus.waxed_oxidized_copper_brick_slab": "Gewachste oxidierte Kupferziegelstufe",
    "block.consistency_plus.waxed_oxidized_copper_brick_stairs": "Gewachste oxidierte Kupferziegeltreppe",
    "block.consistency_plus.waxed_oxidized_copper_brick_wall": "Gewachste oxidierte Kupferziegelmauer",
    "block.consistency_plus.waxed_oxidized_copper_bricks": "Gewachste oxidierte Kupferziegel",
    "block.consistency_plus.waxed_oxidized_copper_pillar": "Gewachste oxidierte Kupfersäule",
    "block.consistency_plus.waxed_oxidized_copper_slab": "Gewachste oxidierte Kupferstufe",
    "block.consistency_plus.waxed_oxidized_copper_stairs": "Gewachste oxidierte Kupfertreppe",
    "block.consistency_plus.waxed_oxidized_copper_tile_gate": "Gewachstes oxidiertes Kupferfliesentor",
    "block.consistency_plus.waxed_oxidized_copper_tile_wall": "Gewachste oxidierte Kupferfliesenmauer",
    "block.consistency_plus.waxed_oxidized_copper_wall": "Gewachste oxidierte Kupfermauer",
    "block.consistency_plus.waxed_oxidized_cut_copper_gate": "Gewachstes oxidiertes geschnittenes Kupfertor",
    "block.consistency_plus.waxed_oxidized_cut_copper_wall": "Gewachste oxidierte geschnittene Kupfermauer",
    "block.consistency_plus.waxed_oxidized_smooth_copper": "Gewachstes oxidiertes glattes Kupfer",
    "block.consistency_plus.waxed_oxidized_smooth_copper_gate": "Gewachstes oxidiertes glattes Kupfertor",
    "block.consistency_plus.waxed_oxidized_smooth_copper_slab": "Gewachste oxidierte glatte Kupferstufe",
    "block.consistency_plus.waxed_oxidized_smooth_copper_stairs": "Gewachste oxidierte glatte Kupfertreppe",
    "block.consistency_plus.waxed_oxidized_smooth_copper_wall": "Gewachste oxidierte glatte Kupferwand",
    "block.consistency_plus.waxed_smooth_copper": "Gewachstes glattes Kupfer",
    "block.consistency_plus.waxed_smooth_copper_gate": "Gewachstes glattes Kupfertor",
    "block.consistency_plus.waxed_smooth_copper_slab": "Gewachste glatte Kupferstufe",
    "block.consistency_plus.waxed_smooth_copper_stairs": "Gewachste glatte Kupfertreppe",
    "block.consistency_plus.waxed_smooth_copper_wall": "Gewachste glatte Kupferwand",
    "block.consistency_plus.waxed_weathered_copper_brick_gate": "Gewachstes verwittertes Kupferziegeltor",
    "block.consistency_plus.waxed_weathered_copper_brick_slab": "Gewachste verwitterte Kupferziegelstufe",
    "block.consistency_plus.waxed_weathered_copper_brick_stairs": "Gewachste verwitterte Kupferziegeltreppe",
    "block.consistency_plus.waxed_weathered_copper_brick_wall": "Gewachste verwitterte Kupferziegelmauer",
    "block.consistency_plus.waxed_weathered_copper_bricks": "Gewachste verwitterte Kupferziegel",
    "block.consistency_plus.waxed_weathered_copper_pillar": "Gewachste verwitterte Kupfersäule",
    "block.consistency_plus.waxed_weathered_copper_slab": "Gewachste verwitterte Kupferstufe",
    "block.consistency_plus.waxed_weathered_copper_stairs": "Gewachste verwitterte Kupfertreppe",
    "block.consistency_plus.waxed_weathered_copper_tile_gate": "Gewachstes verwittertes Kupferfliesentor",
    "block.consistency_plus.waxed_weathered_copper_tile_wall": "Gewachste verwitterte Kupferfliesenmauer",
    "block.consistency_plus.waxed_weathered_copper_wall": "Gewachste verwitterte Kupfermauer",
    "block.consistency_plus.waxed_weathered_cut_copper_gate": "Gewachstes verwittertes geschnittenes Kupfertor",
    "block.consistency_plus.waxed_weathered_cut_copper_wall": "Gewachste verwitterte geschnittene Kupfermauer",
    "block.consistency_plus.waxed_weathered_smooth_copper": "Gewachstes verwittertes glattes Kupfer",
    "block.consistency_plus.waxed_weathered_smooth_copper_gate": "Gewachstes verwittertes glattes Kupfertor",
    "block.consistency_plus.waxed_weathered_smooth_copper_slab": "Gewachste verwitterte glatte Kupferstufe",
    "block.consistency_plus.waxed_weathered_smooth_copper_stairs": "Gewachste verwitterte glatte Kupfertreppe",
    "block.consistency_plus.waxed_weathered_smooth_copper_wall": "Gewachste verwitterte glatte Kupferwand",
    "block.consistency_plus.weathered_copper_brick_gate": "Verwittertes Kupferziegeltor",
    "block.consistency_plus.weathered_copper_brick_slab": "Verwitterte Kupferziegelstufe",
    "block.consistency_plus.weathered_copper_brick_stairs": "Verwitterte Kupferziegeltreppe",
    "block.consistency_plus.weathered_copper_brick_wall": "Verwitterte Kupferziegelmauer",
    "block.consistency_plus.weathered_copper_bricks": "Verwitterte Kupferziegel",
    "block.consistency_plus.weathered_copper_gate": "Verwittertes Kupfertor",
    "block.consistency_plus.weathered_copper_pillar": "Verwitterte Kupfersäule",
    "block.consistency_plus.weathered_copper_slab": "Verwitterte Kupferstufe",
    "block.consistency_plus.weathered_copper_stairs": "Verwitterte Kupfertreppe",
    "block.consistency_plus.weathered_copper_tile_gate": "Verwittertes Kupferfliesentor",
    "block.consistency_plus.weathered_copper_tile_wall": "Verwitterte Kupferfliesenmauer",
    "block.consistency_plus.weathered_copper_wall": "Verwitterte Kupfermauer",
    "block.consistency_plus.weathered_cut_copper_gate": "Verwittertes geschnittenes Kupfertor",
    "block.consistency_plus.weathered_cut_copper_wall": "Verwitterte geschnittene Kupfermauer",
    "block.consistency_plus.weathered_smooth_copper": "Verwittertes glattes Kupfer",
    "block.consistency_plus.weathered_smooth_copper_gate": "Verwittertes glattes Kupfertor",
    "block.consistency_plus.weathered_smooth_copper_slab": "Verwitterte glatte Kupferstufe",
    "block.consistency_plus.weathered_smooth_copper_stairs": "Verwitterte glatte Kupfertreppe",
    "block.consistency_plus.weathered_smooth_copper_wall": "Verwitterte glatte Kupferwand",
    "item.consistency_plus.copper_brick": "Kupferziegel",
    "item.consistency_plus.copper_nugget": "Kupferklumpen",
    "item.consistency_plus.exposed_copper_brick": "Angelaufene Kupferziegel",
    "item.consistency_plus.netherite_nugget": "Netheritklumpen",
    "item.consistency_plus.oxidized_copper_brick": "Oxidierte Kupferziegel",
    "item.consistency_plus.turtle_boots": "Schildkrötenstiefel",
    "item.consistency_plus.waxed_copper_brick": "Gewachste Kupferziegel",
    "item.consistency_plus.waxed_exposed_copper_brick": "Gewachste angelaufene Kupferziegel",
    "item.consistency_plus.waxed_oxidized_copper_brick": "Gewachste oxidierte Kupferziegel",
    "item.consistency_plus.waxed_weathered_copper_brick": "Gewachste verwitterte Kupferziegel",
    "item.consistency_plus.weathered_copper_brick": "Verwitterte Kupferziegel"
}