{
    "advancement.walkietalkie.diamond_walkietalkie.description": "",
    "advancement.walkietalkie.diamond_walkietalkie.title": "",
    "advancement.walkietalkie.golden_walkietalkie.description": "",
    "advancement.walkietalkie.golden_walkietalkie.title": "",
    "advancement.walkietalkie.iron_walkietalkie.description": "",
    "advancement.walkietalkie.iron_walkietalkie.title": "",
    "advancement.walkietalkie.netherite_walkietalkie.description": "",
    "advancement.walkietalkie.netherite_walkietalkie.title": "",
    "advancement.walkietalkie.root.description": "",
    "advancement.walkietalkie.root.title": "",
    "advancement.walkietalkie.stone_walkietalkie.description": "",
    "advancement.walkietalkie.stone_walkietalkie.title": "",
    "advancement.walkietalkie.wooden_walkietalkie.description": "",
    "advancement.walkietalkie.wooden_walkietalkie.title": "",
    "block.walkietalkie.speaker": "",
    "category.walkietalkie.keys": "",
    "gui.walkietalkie.speaker.title": "",
    "gui.walkietalkie.title": "",
    "item.walkietalkie.diamond_walkietalkie": "",
    "item.walkietalkie.golden_walkietalkie": "",
    "item.walkietalkie.iron_walkietalkie": "",
    "item.walkietalkie.netherite_walkietalkie": "",
    "item.walkietalkie.stone_walkietalkie": "",
    "item.walkietalkie.wooden_walkietalkie": "",
    "itemGroup.walkietalkie.walkietalkie": "",
    "key.walkietalkie.activate": ""
}