{
    "block.expandedstorage.bamboo_chest": "Bambustruhe",
    "block.expandedstorage.copper_barrel": "Kupferfass",
    "block.expandedstorage.copper_mini_barrel": "Minikupferfass",
    "block.expandedstorage.exposed_copper_barrel": "Angelaufenes Kupferfass",
    "block.expandedstorage.exposed_copper_mini_barrel": "Angelaufenes Minikupferfass",
    "block.expandedstorage.oxidized_copper_barrel": "Oxidiertes Kupferfass",
    "block.expandedstorage.oxidized_copper_mini_barrel": "Oxidiertes Minikupferfass",
    "block.expandedstorage.waxed_copper_barrel": "Gewachstes Kupferfass",
    "block.expandedstorage.waxed_copper_mini_barrel": "Gewachstes Minikupferfass",
    "block.expandedstorage.waxed_exposed_copper_barrel": "Gewachstes angelaufenes Kupferfass",
    "block.expandedstorage.waxed_exposed_copper_mini_barrel": "Gewachstes angelaufenes Minikupferfass",
    "block.expandedstorage.waxed_oxidized_copper_barrel": "Gewachstes oxidiertes Kupferfass",
    "block.expandedstorage.waxed_oxidized_copper_mini_barrel": "Gewachstes oxidiertes Minikupferfass",
    "block.expandedstorage.waxed_weathered_copper_barrel": "Gewachstes verwittertes Kupferfass",
    "block.expandedstorage.waxed_weathered_copper_mini_barrel": "Gewachstes verwittertes Minikupferfass",
    "block.expandedstorage.weathered_copper_barrel": "Verwittertes Kupferfass",
    "block.expandedstorage.weathered_copper_mini_barrel": "Verwittertes Minikupferfass",
    "entity.expandedstorage.bamboo_chest_minecart": "Bambusgüterlore",
    "item.expandedstorage.bamboo_chest_minecart": "Bambusgüterlore",
    "item.expandedstorage.copper_to_diamond_conversion_kit": "Kupfer-zu-Diamant-Upgrade",
    "item.expandedstorage.copper_to_gold_conversion_kit": "Kupfer-zu-Gold-Upgrade",
    "item.expandedstorage.copper_to_iron_conversion_kit": "Kupfer-zu-Eisen-Upgrade",
    "item.expandedstorage.copper_to_netherite_conversion_kit": "Kupfer-zu-Netherit-Upgrade",
    "item.expandedstorage.copper_to_obsidian_conversion_kit": "Kupfer-zu-Obsidian-Upgrade",
    "item.expandedstorage.diamond_to_netherite_conversion_kit": "Diamant-zu-Netherit-Upgrade",
    "item.expandedstorage.diamond_to_obsidian_conversion_kit": "Diamant-zu-Obsidian-Upgrade",
    "item.expandedstorage.gold_to_diamond_conversion_kit": "Gold-zu-Diamant-Upgrade",
    "item.expandedstorage.gold_to_netherite_conversion_kit": "Gold-zu-Netherit-Upgrade",
    "item.expandedstorage.gold_to_obsidian_conversion_kit": "Gold-zu-Obsidian-Upgrade",
    "item.expandedstorage.iron_to_diamond_conversion_kit": "Eisen-zu-Diamant-Upgrade",
    "item.expandedstorage.iron_to_gold_conversion_kit": "Eisen-zu-Gold-Upgrade",
    "item.expandedstorage.iron_to_netherite_conversion_kit": "Eisen-zu-Netherit-Upgrade",
    "item.expandedstorage.iron_to_obsidian_conversion_kit": "Eisen-zu-Obsidian-Upgrade",
    "item.expandedstorage.obsidian_to_netherite_conversion_kit": "Obsidian-zu-Netherit-Upgrade",
    "item.expandedstorage.wood_to_copper_conversion_kit": "Holz-zu-Kupfer-Upgrade",
    "item.expandedstorage.wood_to_diamond_conversion_kit": "Holz-zu-Diamant-Upgrade",
    "item.expandedstorage.wood_to_gold_conversion_kit": "Holz-zu-Gold-Upgrade",
    "item.expandedstorage.wood_to_iron_conversion_kit": "Holz-zu-Eisen-Upgrade",
    "item.expandedstorage.wood_to_netherite_conversion_kit": "Holz-zu-Netherit-Upgrade",
    "item.expandedstorage.wood_to_obsidian_conversion_kit": "Holz-zu-Obsidian-Upgrade",
    "stat.expandedstorage.open_bamboo_chest": "[ES] Bambustruhen geöffnet",
    "stat.expandedstorage.open_copper_barrel": "[ES] Kupferfässer geöffnet",
    "stat.expandedstorage.open_copper_mini_barrel": "[ES] Minikupferfässer geöffnet",
    "tooltip.expandedstorage.conversion_kit.copper_chests_not_implemented": "Entschuldigung, Kupfertruhen sind noch nicht implementiert worden."
}